agentneo/__init__.py
agentneo/agentneo.py
agentneo/configs/__init__.py
agentneo/configs/model_costs.json
agentneo/data/__init__.py
agentneo/data/data_classes.py
agentneo/data/data_models.py
agentneo/evaluation/__init__.py
agentneo/evaluation/evaluation.py
agentneo/evaluation/metrics/__init__.py
agentneo/evaluation/metrics/goal_decomposition_efficiency.py
agentneo/evaluation/metrics/goal_fulfillment_rate.py
agentneo/evaluation/metrics/plan_adaptibility.py
agentneo/evaluation/metrics/tool_call_correctness_rate.py
agentneo/evaluation/metrics/tool_call_success_rate.py
agentneo/evaluation/metrics/tool_selection_accuracy.py
agentneo/evaluation/metrics/tool_usage_efficiency.py
agentneo/server/__init__.py
agentneo/server/dashboard.py
agentneo/server/dashboard_server.py
agentneo/tracing/__init__.py
agentneo/tracing/agent_tracer.py
agentneo/tracing/base.py
agentneo/tracing/llm_tracer.py
agentneo/tracing/network_tracer.py
agentneo/tracing/tool.py
agentneo/tracing/tool_tracer.py
agentneo/tracing/tracer.py
agentneo/tracing/user_interaction_tracer.py
agentneo/ui/dist/index.html
agentneo/ui/dist/assets/favicon-Btggvy49.svg
agentneo/ui/dist/assets/favicon.svg
agentneo/ui/dist/assets/index-BxKkXIG1.css
agentneo/ui/dist/assets/index-CjY9R8QG.js
agentneo/ui/dist/assets/logo.png
agentneo/utils/__init__.py
agentneo/utils/generic.py
agentneo/utils/llm_utils.py
agentneo/utils/trace_utils.py
agentneo-1.2.3.dist-info/LICENSE
agentneo-1.2.3.dist-info/METADATA
agentneo-1.2.3.dist-info/WHEEL
agentneo-1.2.3.dist-info/top_level.txt
agentneo-1.2.3.dist-info/RECORD
