Metadata-Version: 2.2
Name: agentneo
Version: 1.2.3
Summary: A powerful tracing library for monitoring and analyzing AI agents, LLM calls, and tool interactions.
Author-email: Rehan Asif <rehan.asif@raga.ai>, Kiran Scaria <kiran.scaria@raga.ai>, Vijay Chaurasiya <vijay.chaurasiya@raga.ai>
License: GNU General Public License v3 (GPLv3)
Project-URL: Homepage, https://github.com/raga-ai-hub/agentneo
Project-URL: Bug Tracker, https://github.com/raga-ai-hub/agentneo/issues
Classifier: Development Status :: 4 - Beta
Classifier: Programming Language :: Python :: 3
Classifier: Programming Language :: Python :: 3.9
Classifier: Programming Language :: Python :: 3.10
Classifier: Programming Language :: Python :: 3.11
Classifier: Programming Language :: Python :: 3.12
Classifier: Programming Language :: Python :: 3.13
Classifier: License :: OSI Approved :: GNU General Public License v3 (GPLv3)
Classifier: Operating System :: OS Independent
Requires-Python: >=3.9
License-File: LICENSE
Requires-Dist: sqlalchemy~=2.0.35
Requires-Dist: psutil~=6.0.0
Requires-Dist: py-cpuinfo~=9.0.0
Requires-Dist: requests~=2.32.3
Requires-Dist: GPUtil~=1.4.0
Requires-Dist: wrapt~=1.16
Requires-Dist: Flask~=3.0.2
Requires-Dist: waitress~=2.1.2
Requires-Dist: Flask-Cors~=4.0.1
Requires-Dist: setuptools>=67
Requires-Dist: litellm~=1.49.2
Requires-Dist: openai~=1.51.2
Requires-Dist: langchain~=0.2.16
Requires-Dist: flask_caching~=2.3.0
Requires-Dist: aiohttp~=3.10.4
Provides-Extra: dev
Requires-Dist: pytest; extra == "dev"
Requires-Dist: black; extra == "dev"
Requires-Dist: isort; extra == "dev"
